[
  {
    "id": 18,
    "term": "I need a place to stay tonight.",
    "taxonomies": "BH-1800.3500,BH-1800.8500,BH-7000.4600-800"
  },
  {
    "id": 19,
    "term": "I need help finding housing.",
    "taxonomies": "BH-3800.7250,BH-3900,BH-7000.4600-450,BH-7000.4600-600"
  },
  {
    "id": 20,
    "term": "I need help affording my apartment/home.",
    "taxonomies": "BH-3800.5000,BH-3800.7000,DT-8700.7000-700"
  },
  {
    "id": 21,
    "term": "I need to find a job.",
    "taxonomies": "ND-2000.1500-160,ND-2000.3500,ND-2000.6500,ND-3500"
  },
  {
    "id": 22,
    "term": "I need help paying my utility (gas/electric/heating/fuel/water) bill.",
    "taxonomies": "BV-8900.1700-300,BV-8900.9125-920,BV-8900.9300,BV-8900.9300-950"
  },
  {
    "id": 23,
    "term": "I need to know what kind of help I can get from the state of HI.",
    "taxonomies": "FT-1000,NL-1000.2500,NL-1000.8500,NL-3000.1500,NL-5000.5000,NL-6000.2000,PH-0700"
  },
  {
    "id": 24,
    "term": "I need food.",
    "taxonomies": "BD-1800.1500,BD-1800.2000,BD-5000.1500,BD-5000.3500,BD-5000.8300,BD-5000.8500,NL-6000.2000"
  },
  {
    "id": 25,
    "term": "I need health insurance for myself or my family.",
    "taxonomies": "LH-3500,LH-3500.0200-200,NL-5000.5000,NS-8000.5000"
  },
  {
    "id": 26,
    "term": "I don't have enough money to pay all my bills.",
    "taxonomies": "BV-8900.9125-920,DM-1500.1500,DM-2000,DM-2000,DM-6500,DT-8700.2000-180,NT"
  },
  {
    "id": 27,
    "term": "My child is in crisis and I don't know what to do.",
    "taxonomies": "RP-1500.1400-500,RP-1500.1400,RP-1500.3300"
  },
  {
    "id": 28,
    "term": "I need treatment for a drug or alcohol addiction.",
    "taxonomies": "RX-0400.1500,RX-0400.2500,RX-8450.8000"
  },
  {
    "id": 29,
    "term": "I need help preparing my taxes.",
    "taxonomies": "DT-8700.2000-180,DT-8700.2000-200,DT-8800"
  },
  {
    "id": 30,
    "term": "I need to find a councilor to talk to.",
    "taxonomies": "RD-1900,RF-8380,RP-1400.2500,RP-1400.8000-050,RP-1400.8000-155,RP-1400.8000-675,RP-5000,RR-8500"
  },
  {
    "id": 31,
    "term": "My utilities are going to be shut off.",
    "taxonomies": "BV-8900.9300,BV-8900.9300-850,BV-8900.9300-330,BV-8900.9300-150,BV-8900.9300-950"
  },
  {
    "id": 32,
    "term": "I need transportation.",
    "taxonomies": "BT-4500.4600,BT-4500.4700,BT-4500.6500-170,BT-4500.6500-500,BT-4500.6500-800,BT-8500.1000-180,YL-3500.9400"
  },
  {
    "id": 33,
    "term": "I'm a veteran and need help.",
    "taxonomies": "FT-1000,TJ-3000.8000"
  },
  {
    "id": 34,
    "term": "I'm feeling depressed and need some help.",
    "taxonomies": "RF-8380,RP-1500.1400-500,RP-1500.1400-800,RP-1500.3400-650"
  }
]